aitutor_assessmentkit/__init__.py
aitutor_assessmentkit/autoevaluator/__init__.py
aitutor_assessmentkit/autoevaluator/auto_actionability_eval.py
aitutor_assessmentkit/autoevaluator/auto_autoeval_report.py
aitutor_assessmentkit/autoevaluator/auto_coherence_eval.py
aitutor_assessmentkit/autoevaluator/auto_humanlikeness_eval.py
aitutor_assessmentkit/autoevaluator/auto_mistake_identification_eval.py
aitutor_assessmentkit/autoevaluator/auto_mistake_location_eval.py
aitutor_assessmentkit/autoevaluator/auto_providing_guidance_eval.py
aitutor_assessmentkit/autoevaluator/auto_revealing_of_the_answer_eval.py
aitutor_assessmentkit/autoevaluator/auto_tutor_tone_eval.py
aitutor_assessmentkit/autoevaluator/autoeval.py
aitutor_assessmentkit/helpers/__init__.py
aitutor_assessmentkit/helpers/constants.py
aitutor_assessmentkit/helpers/uptake_utils.py
aitutor_assessmentkit/helpers/utils.py
aitutor_assessmentkit/helpers/vad_utils.py
aitutor_assessmentkit/llmevaluator/__init__.py
aitutor_assessmentkit/llmevaluator/llmeval.py
aitutor_assessmentkit/llmevaluator/prompts.py
aitutor_assessmentkit/llmevaluator/vllm.py
aitutor_assessmentkit/visualizer/__init__.py
aitutor_assessmentkit/visualizer/visualizer.py
aitutor_assessmentkit-0.1.8.dist-info/LICENSE
aitutor_assessmentkit-0.1.8.dist-info/METADATA
aitutor_assessmentkit-0.1.8.dist-info/WHEEL
aitutor_assessmentkit-0.1.8.dist-info/top_level.txt
aitutor_assessmentkit-0.1.8.dist-info/RECORD
