Metadata-Version: 2.1
Name: aitutor-assessmentkit
Version: 0.1.8
Summary: AITutor-AssessmentKit is the first open-source toolkit designed to evaluate the pedagogical performance of AI tutors in student mistake remediation tasks. With the growing capabilities of large language models (LLMs), this library provides a systematic approach to assess their teaching potential across multiple dimensions in educational dialogues.
Home-page: https://github.com/kaushal0494/aitutor-assessmentkit
Author: Kaushal Kumar Maurya
Author-email: Kaushal.Maurya@mbzuai.ac.ae
Classifier: Programming Language :: Python :: 3.10
Classifier: License :: OSI Approved :: MIT License
Classifier: Operating System :: OS Independent
Requires-Python: >=3.10
License-File: LICENSE
Requires-Dist: numpy
Requires-Dist: torch
Requires-Dist: pandas
Requires-Dist: tqdm
Requires-Dist: scipy
Requires-Dist: nltk
Requires-Dist: transformers
Requires-Dist: scikit-learn
Requires-Dist: matplotlib
Requires-Dist: seaborn
Requires-Dist: bert-score
Requires-Dist: clean-text
Requires-Dist: datasets
Requires-Dist: evaluate
Requires-Dist: huggingface-hub
Requires-Dist: llvmlite
Requires-Dist: notebook
Requires-Dist: openai
Requires-Dist: sentencepiece
Requires-Dist: stanza
Requires-Dist: tokenizers
Requires-Dist: num2words
Requires-Dist: vllm
